feffery_antd_mobile_components/Fragment.py
feffery_antd_mobile_components/MobileActionSheet.py
feffery_antd_mobile_components/MobileAutoCenter.py
feffery_antd_mobile_components/MobileAvatar.py
feffery_antd_mobile_components/MobileButton.py
feffery_antd_mobile_components/MobileCapsuleTabs.py
feffery_antd_mobile_components/MobileCard.py
feffery_antd_mobile_components/MobileCascader.py
feffery_antd_mobile_components/MobileCascaderView.py
feffery_antd_mobile_components/MobileCenterPopup.py
feffery_antd_mobile_components/MobileCheckList.py
feffery_antd_mobile_components/MobileCheckbox.py
feffery_antd_mobile_components/MobileCheckboxGroup.py
feffery_antd_mobile_components/MobileCollapse.py
feffery_antd_mobile_components/MobileDialog.py
feffery_antd_mobile_components/MobileDivider.py
feffery_antd_mobile_components/MobileEllipsis.py
feffery_antd_mobile_components/MobileErrorBlock.py
feffery_antd_mobile_components/MobileFloatingBubble.py
feffery_antd_mobile_components/MobileFloatingPanel.py
feffery_antd_mobile_components/MobileFooter.py
feffery_antd_mobile_components/MobileForm.py
feffery_antd_mobile_components/MobileFormHeader.py
feffery_antd_mobile_components/MobileFormItem.py
feffery_antd_mobile_components/MobileGrid.py
feffery_antd_mobile_components/MobileGridItem.py
feffery_antd_mobile_components/MobileIcon.py
feffery_antd_mobile_components/MobileImage.py
feffery_antd_mobile_components/MobileImageViewer.py
feffery_antd_mobile_components/MobileInfiniteScroll.py
feffery_antd_mobile_components/MobileInput.py
feffery_antd_mobile_components/MobileJumboTabs.py
feffery_antd_mobile_components/MobileList.py
feffery_antd_mobile_components/MobileMockPhone.py
feffery_antd_mobile_components/MobileNavBar.py
feffery_antd_mobile_components/MobilePageIndicator.py
feffery_antd_mobile_components/MobilePickerView.py
feffery_antd_mobile_components/MobilePopover.py
feffery_antd_mobile_components/MobilePopup.py
feffery_antd_mobile_components/MobileProgressCircle.py
feffery_antd_mobile_components-0.1.0.dist-info/licenses/LICENSE
feffery_antd_mobile_components-0.1.0.dist-info/METADATA
feffery_antd_mobile_components-0.1.0.dist-info/WHEEL
feffery_antd_mobile_components-0.1.0.dist-info/top_level.txt
feffery_antd_mobile_components-0.1.0.dist-info/RECORD
