Metadata-Version: 2.4
Name: feffery_antd_mobile_components
Version: 0.1.0
Summary: Best implementation of Antd Mobile components for Plotly Dash.
Home-page: https://github.com/CNFeffery/feffery-antd-mobile-components
Author: CNFeffery <fefferypzy@gmail.com>
Author-email: fefferypzy@gmail.com
License: MIT
Classifier: Framework :: Dash
License-File: LICENSE
Requires-Dist: dash>=3.1.0
Dynamic: author
Dynamic: author-email
Dynamic: classifier
Dynamic: home-page
Dynamic: license
Dynamic: license-file
Dynamic: requires-dist
Dynamic: summary
